[{"s": "abs-gazel-biznes", "t": "ABS Газель Бизнес: Устройство, неисправности и ремонт системы", "i": "📁", "c": "тормозная-система"}, {"s": "abs-na-gazel-nekst", "t": "АБС на Газель NEXT: устройство, коды ошибок и ремонт", "i": "📁", "c": "тормозная-система"}, {"s": "absorber-gazel-biznes", "t": "Абсорбер Газель Бизнес: признаки неисправности и замена", "i": "📁", "c": "двигатель"}, {"s": "absorber-na-gazel", "t": "Абсорбер на Газель: признаки неисправности и замена", "i": "📁", "c": "топливная-система-и-гбо"}, {"s": "abs-gazel-nekst", "t": "ABS Газель Некст: устройство, неисправности и ремонт системы", "i": "📁", "c": "тормозная-система"}, {"s": "abri-sleep-box-dlya-gazel", "t": "Abri Sleep Box для Газель: обзор, установка и характеристики", "i": "📁", "c": "салон-и-комфорт"}, {"s": "absorber-gazel-nekst-evotek", "t": "Абсорбер Газель Некст Эвотек: признаки неисправности и замена", "i": "📁", "c": "топливная-система-и-гбо"}, {"s": "abs-na-gazel-biznes", "t": "ABS на Газель Бизнес: устройство, датчики и устранение неисправностей", "i": "📁", "c": "тормозная-система"}]