[{"s": "kitajskie-shiny-na-gazel", "t": "Китайские шины на Газель: ТОП-5 брендов, отзывы и выбор", "i": "📁", "c": "сравнения-и-выбор"}, {"s": "kipit-gazel-402-dvigatel", "t": "Кипит Газель 402 двигатель: причины и срочное устранение", "i": "📁", "c": "система-охлаждения"}, {"s": "kislorodnyj-datchik-gazel-biznes", "t": "Кислородный датчик Газель Бизнес: признаки, замена и диагностика", "i": "📁", "c": "двигатель"}, {"s": "kitajskaya-gazel-analog", "t": "Китайская Газель аналог: обзор, характеристики и сравнение моделей", "i": "📁", "c": "сравнения-и-выбор"}, {"s": "kislorodnyj-datchik-gazel-nekst", "t": "Кислородный датчик Газель NEXT: признаки неисправности и замена", "i": "📁", "c": "двигатель"}, {"s": "kitajskij-dvigatel-na-gazel", "t": "Китайский двигатель на Газель: выбор, установка и характеристики", "i": "📁", "c": "двигатель"}, {"s": "kitajskaya-gazel-gruzovaya", "t": "Китайская Газель грузовая: обзор моделей, характеристики и выбор", "i": "📁", "c": "сравнения-и-выбор"}, {"s": "kitajskaya-rezina-na-gazel-185-75-r16c", "t": "Китайская резина на Газель 185 75 R16C: ТОП-5 брендов и тесты", "i": "📁", "c": "мосты,-ступицы-и-колёса"}, {"s": "kirovskaya-rezina-na-gazel", "t": "Кировская резина на Газель: обзор, отзывы и тесты", "i": "📁", "c": "мосты,-ступицы-и-колёса"}, {"s": "kislorodnyj-datchik-gazel-4216", "t": "Кислородный датчик Газель 4216: признаки неисправности и замена", "i": "📁", "c": "электрика-и-электроника"}, {"s": "kitajskaya-rezina-na-gazel", "t": "Китайская резина на Газель: ТОП брендов, отзывы и выбор шин", "i": "📁", "c": "мосты,-ступицы-и-колёса"}, {"s": "kipit-gazel-402-dvigatel-prichiny", "t": "Кипит Газель 402: причины перегрева и методы решения", "i": "📁", "c": "система-охлаждения"}, {"s": "kitajskie-shiny-na-gazel-185-75-r16c", "t": "Китайские шины 185/75 R16C на Газель: выбор, бренды и отзывы", "i": "📁", "c": "мосты,-ступицы-и-колёса"}]