[{"s": "ugly-ustanovki-koles-gazel", "t": "Углы установки колес Газель: регулировка, нормы и ошибки", "i": "📁", "c": "подвеска-и-рулевое"}, {"s": "ugolok-zerkala-gazel-nekst-levyj", "t": "Левый уголок зеркала Газель Некст: подбор, установка, ремонт", "i": "📁", "c": "кузов-и-кабина"}, {"s": "ugolok-dlya-budki-gazel", "t": "Уголок для будки Газель: размеры, чертежи и монтаж своими руками", "i": "📁", "c": "кузов-и-кабина"}, {"s": "ugolok-na-budku-gazel", "t": "Уголок на будку Газель: виды, установка и цены", "i": "📁", "c": "кузов-и-кабина"}, {"s": "ugolok-budki-gazel-nekst", "t": "Уголок будки Газель Некст: размеры, установка, чертежи и фото", "i": "📁", "c": "кузов-и-кабина"}, {"s": "ugol-zerkala-gazel-nekst", "t": "Угол зеркала Газель Некст: регулировка, ремонт и замена", "i": "📁", "c": "кузов-и-кабина"}, {"s": "ugolok-na-budku-furgona-gazel", "t": "Уголок на будку Газель: размеры, чертежи и установка своими руками", "i": "📁", "c": "кузов-и-кабина"}, {"s": "ugolok-na-furgon-gazel", "t": "Уголок на фургон Газель: выбор, установка и усиление кузова", "i": "📁", "c": "кузов-и-кабина"}, {"s": "ugol-kabiny-gazel-3302-levyj", "t": "Левый угол кабины Газель 3302: ремонт, замена и защита", "i": "📁", "c": "кузов-и-кабина"}, {"s": "ugolki-na-budku-gazel", "t": "Уголки на будку Газель: установка, размеры и чертежи", "i": "📁", "c": "кузов-и-кабина"}]